mcp_taxcode/__init__.py
mcp_taxcode/server.py
mcp_taxcode-0.1.0.dist-info/METADATA
mcp_taxcode-0.1.0.dist-info/WHEEL
mcp_taxcode-0.1.0.dist-info/entry_points.txt
mcp_taxcode-0.1.0.dist-info/RECORD
