Metadata-Version: 2.4
Name: mcp-taxcode
Version: 0.1.0
Summary: MCP server for searching the US Tax Code (IRC)
Author: eugene
License: MIT
Requires-Python: >=3.10
Requires-Dist: httpx>=0.28.0
